[
    {
        "ONE 체크카드": {
            "혜택 요약": "최대 1.2% 캐시백 (3개 중 1개 선택), 자주 쓰는 곳에서 7% 캐시백 (3개 중 1개 선택), 3번 결제할 때마다 1,000원 캐시백 (3개 중 1개 선택)",
            "연회비 상세안내": "해외겸용(VISA) 없음",
            "주요 혜택": {
                "대중교통": "대중교통 혜택 추가 3천원 캐시백",
                "캐시백": "[369 캐시백] 3번 결제할 때마다 1,000원 캐시백",
                "기타": "기본 혜택",
                "유의사항": "꼭 확인하세요!"
            },
            "카드 이미지": "card_image/check_card\\2749card_2.png"
        }
    },
    {
        "노리2 체크카드(KB Pay)": {
            "혜택 요약": "커피, 모바일, 문화 10% 할인, 뷰티, 편의점 5% 할인, KB Pay 2% 추가 할인",
            "연회비 상세안내": "국내전용(Local) 없음 해외겸용(VISA, Mastercard) 없음",
            "주요 혜택": {
                "카페": "[일상] 스타벅스, 커피빈 10% 할인",
                "게임": "[일상] 구글플레이스토어, 앱스토어 10% 할인",
                "공연/전시": "[일상] 인터파크 티켓 10% 할인",
                "드럭스토어": "[일상] 올리브영, 미용실 업종 5% 할인",
                "편의점": "[일상] GS25, CU 5% 할인",
                "디지털구독": "[일상]넷플릭스, 유튜브프리미엄 1,000원 할인",
                "배달앱": "[일상] 배달의 민족, 요기요 1,000원 할인",
                "통신": "[일상] SKT, KT, LG U+, Liiv M 2,500원 할인",
                "영화": "[일상] CGV 4,000원 할인",
                "테마파크": "[일상] 에버랜드, 롯데월드 15,000원 할인",
                "간편결제": "[KB Pay] 온라인 가맹점 2% 추가 할인",
                "유의사항": "꼭 확인하세요!"
            },
            "카드 이미지": "card_image/check_card\\2422card.png"
        }
    },
    {
        "신한카드 Deep Dream 체크(미니언즈)": {
            "혜택 요약": "모두드림 0.2% 적립, 더해드림 0.6% 적립, 챙겨드림 1.0% 적립",
            "연회비 상세안내": "해외겸용(VISA) 없음",
            "주요 혜택": {
                "적립": "[반겨드림] 반겨드림 3천 포인트 적립",
                "생활": "[챙겨드림] DREAM영역 중 가장 많이 이용한 영역은 기본의 5배 (총 1.0%) 포인트 자동적립",
                "주유소": "주말(토,일) 전 주유소 리터당 40원 적립",
                "택시": "택시 3,6,9번째 1천원 할인",
                "유의사항": "꼭 확인하세요!"
            },
            "카드 이미지": "card_image/check_card\\646card.png"
        }
    },
    {
        "네이버페이 머니 하나 체크카드": {
            "혜택 요약": "네이버페이 1.2% 포인트 적립, , ",
            "연회비 상세안내": "국내전용(Local) 없음 해외겸용(mastercard) 없음",
            "주요 혜택": {
                "적립": "네이버페이 포인트 적립 서비스",
                "선택형": "플레이트 디자인 선택 가능",
                "유의사항": "꼭 확인하세요!"
            },
            "카드 이미지": "card_image/check_card\\2432card.png"
        }
    },
    {
        "카카오페이 신한 체크카드": {
            "혜택 요약": "카카오페이 2% 적립, 대중교통 3% 적립, CGV 최대 3천원 적립",
            "연회비 상세안내": "해외겸용(Mastercard) 없음",
            "주요 혜택": {
                "선택형": "플레이트 디자인 선택 가능",
                "카카오페이": "카카오페이 결제 시 2% 적립",
                "대중교통": "대중교통 3% 적립",
                "통신": "이동통신요금 3% 적립",
                "영화": "CGV 영화 최대 3천원 적립",
                "해외": "해외 전가맹점(온라인 포함) 이용금액 1% 적립,해외 인출 1건당 US $3 적립 제공",
                "프리미엄 서비스": "Master 플래티늄 서비스",
                "유의사항": "꼭 확인하세요!"
            },
            "카드 이미지": "card_image/check_card\\286card.png"
        }
    },
    {
        "PAYCO 포인트 카드": {
            "혜택 요약": "최대 1% 무한적립, HDC아이파크몰 100만P 상품권 지급, 매월 건당 최대 30% 무제한 할인",
            "연회비 상세안내": "해외겸용(VISA) 없음",
            "주요 혜택": {
                "적립": "매월 바뀌는 브랜드에서 건당 최대 10% 적립",
                "할인": "매월 바뀌는 브랜드에서 건당 최대 30% 할인",
                "기타": "해외결제, 포인트결제 소득공제, ATM 출금 월 2회 무료, 교통카드기능",
                "유의사항": "꼭 확인하세요!"
            },
            "카드 이미지": "card_image/check_card\\2310card.png"
        }
    },
    {
        "더나은 체크카드": {
            "혜택 요약": "간편결제 20% 할인, 온라인쇼핑 20% 할인, 커피전문점 20% 할인",
            "연회비 상세안내": "해외겸용(VISA) 없음",
            "주요 혜택": {
                "간편결제": "네이버페이, 카카오페이, 페이코 결제 시 이용금액의 20% 할인 캐시백",
                "온라인쇼핑": "쿠팡, 무신사, 지그재그, W컨셉, 에이블리 결제 시 이용금액의 20% 할인 캐시백",
                "카페": "스타벅스, 투썸플레이스, 커피빈, 메가커피, 빽다방, 컴포즈커피 결제 시 이용금액의 20% 할인 캐시백",
                "해외이용": "해외 서비스수수료, 현금인출수수료, 예금잔액조회수수료 면제",
                "유의사항": "꼭 확인하세요!"
            },
            "카드 이미지": "card_image/check_card\\2601card.png"
        }
    },
    {
        "모빌리언스카드": {
            "혜택 요약": "결제 금액 0.5% 적립, 바코드결제 최대 7.5% 즉시적립, KFC 10% 즉시할인",
            "연회비 상세안내": "국내전용(Local) 없음 발급 수수료 없음(단, 재발급 수수료는 회사의 사정에 따라 부과될 수 있습니다.)",
            "주요 혜택": {
                "모든가맹점": "온라인 1% / 오프라인 0.5% 무제한 적립",
                "온라인쇼핑": "모빌마켓 이용 시 2% 무제한 적립",
                "편의점": "GS25, 이마트24 1.5% 적립",
                "카페": "카페/베이커리 브랜드 최대 7.5% 적립",
                "생활": "대형마트/쇼핑/여가 브랜드 최대 6.5% 적립",
                "푸드": "외식 브랜드 최대 6.5% 적립",
                "패스트푸드": "KFC 10% 즉시할인",
                "통신": "KG모바일 알뜰폰 결합 시 4.5% 혜택",
                "기타": "페이북 및 간편결제 가능, 마이태그 캐시백 혜택 적용",
                "혜택 프로모션": "휴대폰결제로 충전 후 최초 결제 시 2,000P 즉시 지급 + 매월 신규 이벤트 진행 중",
                "유의사항": "꼭 확인하세요!"
            },
            "카드 이미지": "card_image/check_card\\2321card.png"
        }
    },
    {
        "노리체크카드": {
            "혜택 요약": "대중교통 10% 청구할인, 이동통신요금 2,500원 환급할인, CGV 35% 환급할인",
            "연회비 상세안내": "국내전용 없음 해외겸용(VISA, Mastercard, UnionPay) 없음 *후불교통카드 발급가능",
            "주요 혜택": {
                "대중교통": "버스·지하철 10% 청구할인",
                "통신": "이동통신요금 2,500원 환급할인",
                "영화": "CGV 35% 환급할인",
                "푸드": "아웃백, VIPS / 스타벅스 20% 환급할인",
                "테마파크": "에버랜드·롯데월드 50% 환급할인",
                "금융": "금융수수료 면제 서비스",
                "편의점": "GS25 5% 환급할인",
                "도서": "교보문고 5% 환급할인",
                "유의사항": "꼭 확인하세요!"
            },
            "카드 이미지": "card_image/check_card\\348card.png"
        }
    },
    {
        "네이버페이 머니카드": {
            "혜택 요약": "해외 온/오프라인 3% 적립, 네이버 쇼핑 1.5% 적립, 국내 온/오프라인 0.3% 적립",
            "연회비 상세안내": "국내전용(Local) 없음 해외겸용(VISA) 없음",
            "주요 혜택": {
                "해외": "해외 온/오프라인 3% 적립",
                "여행/숙박": "N트래블클럽 업그레이드",
                "적립": "플러스 멤버십 스튜던트 정기결제 10% 적립",
                "유의사항": "꼭 확인하세요!"
            },
            "카드 이미지": "card_image/check_card\\2625card_1.png"
        }
    },
    {
        "네이버페이 우리카드 체크": {
            "혜택 요약": "네이버페이 1% 적립, 공항라운지 무료 이용, 해외수수료 면제 서비스",
            "연회비 상세안내": "국내전용(BC) 5,000원 해외겸용(MasterCard) 5,000원",
            "주요 혜택": {
                "네이버페이": "네이버페이 포인트 1% 적립",
                "공항라운지": "국내외 공항라운지 무료 이용 서비스",
                "수수료우대": "해외이용수수료 면제",
                "프리미엄 서비스": "MasterCard Platinum 서비스 제공",
                "유의사항": "꼭 확인하세요!"
            },
            "카드 이미지": "card_image/check_card\\588card.png"
        }
    },
    {
        "토스뱅크카드": {
            "혜택 요약": "카페·패스트푸드·택시 등 최대 500원 캐시백, 어디서나 100원 또는 1% 캐시백, 해외 ATM 수수료 면제 혜택",
            "연회비 상세안내": "해외겸용(Mastercard) 없음 *발급수수료 2,000원(별도 안내 전까지 프로모션으로 면제 혜택 지속 제공)",
            "주요 혜택": {
                "캐시백": "기부 캐시백",
                "해외": "ATM 현금 인출 수수료 혜택/해외 온・오프라인 결제 무제한 캐시백",
                "유의사항": "꼭 확인하세요!"
            },
            "카드 이미지": "card_image/check_card\\2269card.png"
        }
    },
    {
        "카드의정석 오하CHECK": {
            "혜택 요약": "온라인 쇼핑 5% 캐시백, 간편결제 5% 캐시백, 스타벅스 5% 캐시백",
            "연회비 상세안내": "국내전용(Local) 없음 해외겸용(Mastercard) 없음",
            "주요 혜택": {
                "온라인쇼핑": "[오늘 하루 SHOPPING] 온라인 쇼핑  5% 캐시백",
                "간편결제": "[오늘 하루 SHOPPING] 간편결제 5% 캐시백",
                "생활": "[오늘 하루 LIFE] 어학시험 5% 캐시백",
                "카페": "[오늘 하루 EAT] 커피 5% 캐시백",
                "배달앱": "[오늘 하루 EAT] 배달/주문 5% 캐시백",
                "대중교통": "[오늘 하루 LIFE] 대중교통(버스/지하철) 5% 캐시백",
                "통신": "[오늘 하루 LIFE] 이동통신 5% 캐시백",
                "해외": "[오늘 하루 LIFE] 해외 5% 캐시백",
                "디지털구독": "[오늘 하루 PLAY] OTT 5% 캐시백",
                "공연/전시": "[오늘 하루 PLAY] 공연티켓 5% 캐시백",
                "유의사항": "꼭 확인하세요!"
            },
            "카드 이미지": "card_image/check_card\\2570card.png"
        }
    },
    {
        "신한카드 Deep Dream 체크": {
            "혜택 요약": "모두드림 0.2% 적립, 더해드림 0.6% 적립, 챙겨드림 1.0% 적립",
            "연회비 상세안내": "해외겸용(VISA) 없음",
            "주요 혜택": {
                "적립": "추가 포인트 적립",
                "생활": "추가 포인트 적립",
                "주유소": "주유소 적립",
                "택시": "택시 할인",
                "금융": "수수료 우대",
                "유의사항": "꼭 확인하세요!"
            },
            "카드 이미지": "card_image/check_card\\281card.png"
        }
    },
    {
        "신한카드 SOL트래블 체크": {
            "혜택 요약": "해외 이용 수수료 면제, 더라운지 무료 입장, 해외 대중교통 1% 할인",
            "연회비 상세안내": "국내전용(Local) 없음 해외겸용(mastercard) 없음",
            "주요 혜택": {
                "해외이용": "해외이용 프로모션",
                "수수료우대": "국제 브랜드 수수료(1%)/해외 서비스 수수료(0.2%) 면제",
                "공항라운지": "더라운지 공항라운지 본인 무료 입장",
                "해외": "해외 대중교통 컨택리스 방식으로 이용 시 1% 결제일 할인",
                "할인": "국내 4대 편의점 5% 결제일 할인국내 대중교통 1% 결제일 할인",
                "유의사항": "꼭 확인하세요!"
            },
            "카드 이미지": "card_image/check_card\\2660card.png"
        }
    },
    {
        "노리2 체크카드(Global)": {
            "혜택 요약": "커피,모바일,문화 10% 할인, 해외 가맹점 2% 할인, 공항라운지 연 1회 이용권",
            "연회비 상세안내": "국내전용(Local) 없음 해외겸용(Mastercard) 없음",
            "주요 혜택": {
                "카페": "[일상] 스타벅스, 커피빈 10% 할인",
                "게임": "[일상] 구글플레이스토어, 앱스토어 10% 할인",
                "공연/전시": "[일상] 인터파크 티켓 10% 할인",
                "드럭스토어": "[일상] 올리브영, 미용실 업종 5% 할인",
                "편의점": "[일상] GS25, CU 5% 할인",
                "디지털구독": "[일상]넷플릭스, 유튜브프리미엄 1,000원 할인",
                "배달앱": "[일상] 배달의 민족, 요기요 1,000원 할인",
                "통신": "[일상] SKT, KT, LG U+, Liiv M 2,500원 할인",
                "OTT/영화/문화": "[일상] CGV 4,000원 할인",
                "테마파크": "[일상] 에버랜드, 롯데월드 15,000원 할인",
                "해외이용": "[Global] 해외 가맹점 2% 할인",
                "공항라운지": "[Global] 공항라운지 더라운지멤버스",
                "유의사항": "꼭 확인하세요!"
            },
            "카드 이미지": "card_image/check_card\\2423card.png"
        }
    },
    {
        "토심이 첵첵 체크카드": {
            "혜택 요약": "대중교통 2~4천원 할인, 온라인간편결제 2~4천원 할인, 스타벅스 2~4천원 할인",
            "연회비 상세안내": "국내전용(Local) 없음 해외겸용(Mastercard) 없음",
            "주요 혜택": {
                "대중교통": "버스·지하철 2~4천원 청구할인",
                "편의점": "CU편의점 2~4천원 환급할인",
                "카페": "스타벅스(사이렌오더 포함) 2~4천원 환급할인",
                "영화": "CGV 2~4천원 환급할인",
                "쇼핑": "텐바이텐 2~4천원 환급할인",
                "간편결제": "네이버페이·카카오페이·SSG페이 2~4천원 환급할인 (온라인만)",
                "뷰티/피트니스": "올리브영, 안경(렌즈)점 2~4천원 환급할인",
                "도서": "YES24, 교보문고 2~4천원 환급할인 (온라인만)",
                "공연/전시": "인터파크티켓 2~4천원 환급할인 (온라인만)",
                "유의사항": "꼭 확인하세요!"
            },
            "카드 이미지": "card_image/check_card\\2604card.png"
        }
    },
    {
        "네이버페이 신한카드 체크 S2": {
            "혜택 요약": "네이버 최대 2% 적립, 네이버 외 0.1% 적립, ",
            "연회비 상세안내": "국내전용 없음 해외겸용(VISA) 없음",
            "주요 혜택": {
                "네이버페이": "네이버에서 결제 시 1~2% 적립",
                "적립": "네이버 외 결제 시 0.1% 적립"
            },
            "카드 이미지": "card_image/check_card\\2268card.png"
        }
    },
    {
        "트래블러스 체크카드": {
            "혜택 요약": "해외 이용 수수료 면제, 철도 5,000원 할인, 전국맛집 5,000원 할인",
            "연회비 상세안내": "연회비 없음",
            "주요 혜택": {
                "해외": "[해외 혜택] 해외 가맹점, ATM 이용 수수료 면제",
                "할인": "[국내 혜택] KB Pay 200원 추가 할인",
                "카페": "[국내 혜택] 카페 1,000원 할인",
                "베이커리": "[국내 혜택] 빵집 2,000원 할인",
                "기차": "[국내 혜택] 철도 5,000원 할인",
                "고속버스": "[국내 혜택] 고속버스 2,000원 할인",
                "자동차": "[국내 혜택] 주차장 500원 할인",
                "푸드": "[국내 혜택] 전국맛집 5,000원 할인",
                "유의사항": "꼭 확인하세요!"
            },
            "카드 이미지": "card_image/check_card\\2691card_2.png"
        }
    },
    {
        "카카오뱅크 프렌즈 체크카드": {
            "혜택 요약": "국내외 가맹점 0.2~0.4% 캐시백, 학원 업종 1만원 캐시백, 배달의민족 1천원 캐시백",
            "연회비 상세안내": "해외겸용(Mastercard) 없음",
            "주요 혜택": {
                "모든가맹점": "조건 없이 캐시백, 평일 0.2% 주말/공휴일 0.4%",
                "생활": "카카오뱅크 프렌즈 체크카드 캐시백 프로모션 2025",
                "대중교통": "부릉부릉 K-패스 혜택 카드",
                "선택형": "내 마음에 드는 디자인 선택의 즐거움",
                "유의사항": "꼭 확인하세요!"
            },
            "카드 이미지": "card_image/check_card\\435card.png"
        }
    },
    {
        "신한카드 Hey Young 체크": {
            "혜택 요약": "대중교통 5% 캐시백, 영화 5천원 캐시백, 간편결제 1% 캐시백",
            "연회비 상세안내": "국내전용 없음 해외겸용(VISA Platinum) 없음",
            "주요 혜택": {
                "선택형": "플레이트 디자인 선택 가능",
                "대중교통": "대중교통 이용금액 5% 캐시백",
                "통신": "이동통신요금 자동이체 시 2천원 캐시백",
                "영화": "CGV 영화 예매 5천원 캐시백",
                "편의점": "GS25 편의점 1천원 캐시백",
                "카페": "스타벅스 커피 1천원 캐시백(사이렌오더, FAN사이렌 오더 포함)",
                "온라인쇼핑": "쿠팡 1천원 캐시백",
                "간편결제": "간편결제(Pay)로 국내 이용 시 1% 캐시백",
                "해외": "해외 전 가맹점(온라인포함) 1.2% 캐시백해외인출 1건 당 US $3 캐시백 제공",
                "유의사항": "꼭 확인하세요!"
            },
            "카드 이미지": "card_image/check_card\\618card.png"
        }
    },
    {
        "직장인보너스체크카드": {
            "혜택 요약": "국세/지방세 7,000원 할인, GS칼텍스 60~50원/L 할인, 백화점 5% 할인",
            "연회비 상세안내": "국내전용 없음 해외겸용(VISA, mastercard) 없음 * 후불교통카드 : 가능",
            "주요 혜택": {
                "공과금/렌탈": "국세·지방세 7천원 환급할인",
                "주유소": "GS칼텍스 리터당 주중 50원, 주말 60원 환급할인",
                "정비": "스피드메이트 엔진오일교환 2만원 현장할인 및 정비 할인",
                "렌터카": "SK렌터카 할인 (연 2회)",
                "백화점": "롯데·현대·신세계백화점 5% 환급할인",
                "패밀리레스토랑": "아웃백 10% 환급할인",
                "대중교통": "버스·지하철 5% 청구할인",
                "통신": "이동통신요금 1,000원 환급할인 (월 1회)",
                "테마파크": "에버랜드 50% 환급할인",
                "해피포인트": "해피포인트 5% 현장적립",
                "기타": "통합할인한도",
                "유의사항": "꼭 확인하세요!"
            },
            "카드 이미지": "card_image/check_card\\350card.png"
        }
    },
    {
        "청춘대로 싱글 체크카드": {
            "혜택 요약": "편의점 10~5% 할인, 다이소/소셜커머스 10~5% 할인, 동물병원 10% 할인",
            "연회비 상세안내": "해외겸용(mastercard, UnionPay) 없음\n*후불교통카드 발급가능",
            "주요 혜택": {
                "편의점": "편의점 업종 5~10% 환급할인",
                "소셜커머스": "다이소/소셜커머스 5~10% 환급할인",
                "교통": "대중교통, 택시 5% 환급할인",
                "애완동물": "올리브영·박승철헤어스투디오/동물병원 10% 환급할인",
                "해외이용": "해외이용/해외직구 할인캐시백",
                "여행/숙박": "라이프샵 여행 해외패키지 3% 현장할인",
                "유의사항": "꼭 확인하세요!"
            },
            "카드 이미지": "card_image/check_card\\335card.png"
        }
    },
    {
        "춘식이달달체크카드": {
            "혜택 요약": "커피·편의점·영화·온라인쇼핑·배달앱 최대 1% 적립, OTT 5% 적립, 국제공항 라운지 무료이용 서비스",
            "연회비 상세안내": "국내전용(Local) 없음 해외겸용(Mastercard) 없음",
            "주요 혜택": {
                "적립": "Triple Point (요일 관계없이 1.5% NH포인트 적립)",
                "디지털구독": "Bonus Point (유튜브, 넷플릭스, 유료 어플리케이션 결제 5% NH포인트 적립)",
                "공항라운지": "국제공항 라운지 무료이용 서비스",
                "유의사항": "꼭 확인하세요!"
            },
            "카드 이미지": "card_image/check_card\\2758card_1.png"
        }
    },
    {
        "NH20해봄체크카드": {
            "혜택 요약": "온라인쇼핑몰 5% 할인, 배달앱 5% 할인, 커피 20% 할인",
            "연회비 상세안내": "국내전용 없음 해외겸용(mastercard) 없음 * 후불교통카드 : 가능",
            "주요 혜택": {
                "선택형": "해봄 선택 서비스_여행해봄/놀이해봄 Type 중 택1",
                "온라인쇼핑": "[On-Line 서비스]",
                "생활": "[Off-Line 서비스]",
                "멤버십포인트": "GS리테일 POP 서비스",
                "기타": "주요서비스 통합 월 할인한도",
                "유의사항": "꼭 확인하세요!"
            },
            "카드 이미지": "card_image/check_card\\362card.png"
        }
    },
    {
        "K-패스 신한카드 체크": {
            "혜택 요약": "대중교통 10% 할인, 간편결제 2% 할인, 생활 부문 2% 할인",
            "연회비 상세안내": "국내전용(Local) 없음 해외겸용(Mastercard) 없음",
            "주요 혜택": {
                "대중교통": "대중교통(버스, 지하철) 이용 시 10% 결제일 할인",
                "간편결제": "간편결제로 결제 시 2% 결제일 할인",
                "생활": "생활서비스 2% 결제일 할인",
                "유의사항": "꼭 확인하세요"
            },
            "카드 이미지": "card_image/check_card\\2692card.png"
        }
    },
    {
        "신한카드 On 체크(잔망루피)": {
            "혜택 요약": "간편결제 2% 적립, 생활편의 2% 적립, 해외 이용금액 1.3% 적립",
            "연회비 상세안내": "국내전용(Local) 없음 해외겸용(VISA) 없음",
            "주요 혜택": {
                "간편결제": "간편결제(Pay) 이용 시 최대 2% 적립",
                "생활": "생활편의영역 이용 시 최대 2% 적립 ",
                "해외": "해외 이용금액에 대해 1.3% 적립",
                "선택형": "카드 플레이트 선택 가능",
                "유의사항": "꼭 확인하세요!"
            },
            "카드 이미지": "card_image/check_card\\2379card.png"
        }
    },
    {
        "네이버페이 신한카드 체크": {
            "혜택 요약": "전가맹점 1% 적립, , ",
            "연회비 상세안내": "국내전용 없음 해외겸용(VISA) 없음 * 후불교통카드: 발급 가능 * 네이버페이 체크카드는 네이버페이 사이트를 통해서만 카드 신청이 가능합니다.",
            "주요 혜택": {
                "네이버페이": "네이버페이포인트 1% 적립",
                "유의사항": "꼭 확인하세요!"
            },
            "카드 이미지": "card_image/check_card\\460card.png"
        }
    },
    {
        "트래블로그 체크카드": {
            "혜택 요약": "해외 가맹점 이용 수수료 면제, 해외 ATM 인출 수수료 면제, ",
            "연회비 상세안내": "해외겸용(mastercard, UnionPay) 없음 *본 체크카드는 발급수수료 2,000원이 부과되며 카드수령 다음달 말일까지 1만원 이상 이용시 발급수수료를 돌려드립니다",
            "주요 혜택": {
                "해외이용": "해외 가맹점 이용수수료 면제",
                "수수료우대": "해외 ATM 인출 수수료 면제",
                "적립": "국내 가맹점 이용 시 0.3% 적립",
                "선택형": "플레이트 3종 선택",
                "유의사항": "꼭 확인하세요!"
            },
            "카드 이미지": "card_image/check_card\\2394card.png"
        }
    },
    {
        "달달 하나 체크카드": {
            "혜택 요약": "간편결제 0.3% 적립, 쇼핑 5% 적립, 구독 10% 적립",
            "연회비 상세안내": "국내전용(Local) 없음 해외겸용(VISA, Mastercard) 없음",
            "주요 혜택": {
                "적립": "하나머니 적립 서비스",
                "유의사항": "꼭 확인하세요!"
            },
            "카드 이미지": "card_image/check_card\\2750card_1.png"
        }
    },
    {
        "올바른POINT체크카드": {
            "혜택 요약": "전 가맹점 0.4~0.2% 적립, 해외 0.3% 추가적립, 국제공항라운지 무료 이용",
            "연회비 상세안내": "해외겸용(VISA) 없음 * 후불교통카드 : 가능",
            "주요 혜택": {
                "모든가맹점": "적립한도 없이 0.2% ~ 0.7% NH포인트 적립",
                "공항라운지": "국제공항 라운지 무료이용",
                "은행사": "전자금융 수수료 면제",
                "유의사항": "꼭 확인하세요!"
            },
            "카드 이미지": "card_image/check_card\\360card.png"
        }
    },
    {
        "카드의정석 EVERY CHECK": {
            "혜택 요약": "국내외 가맹점 0.2% 적립, 전월실적에 따라 최대 3천원 추가 적립, 공연·테마파크·영화·여행 중 한 곳 1만원 적립",
            "연회비 상세안내": "국내전용(Local) 없음 해외겸용(mastercard) 없음 ※ 가족카드 발급 불가",
            "주요 혜택": {
                "무실적": "[기본 적립] 국내외 가맹점 이용금액 0.2% 적립",
                "적립": "[특별 적립] 4대 일상영역 중 한 곳 1만원 적립",
                "선택형": "플레이트 3종 선택",
                "유의사항": "꼭 확인하세요!"
            },
            "카드 이미지": "card_image/check_card\\2552card.png"
        }
    },
    {
        "K-패스카드(체크)": {
            "혜택 요약": "대중교통 10% 할인, 렌터카/카쉐어링 5% 할인, 전기차 충전 5% 할인",
            "연회비 상세안내": "국내전용(Local) 없음 해외겸용(VISA) 없음",
            "주요 혜택": {
                "교통": "[모빌리티 서비스] 버스/지하철 10% 캐시백, 렌터카/카쉐어링/전기차 충전 5% 캐시백",
                "통신": "[라이프 서비스] 이동통신요금/커피전문점/편의점 5% 캐시백",
                "유의사항": "꼭 확인하세요!"
            },
            "카드 이미지": "card_image/check_card\\2561card.png"
        }
    },
    {
        "신한카드 플리 체크(산리오캐릭터즈)": {
            "혜택 요약": "국내 이용금액 최대 0.3% 할인, 해외 이용금액 0.2% 할인, 매 월 2회 할인쿠폰 제공",
            "연회비 상세안내": "국내전용(Local) 없음 해외겸용(Mastercard) 없음",
            "주요 혜택": {
                "국내외가맹점": "[Daily 할인] 국내 이용금액 최대 0.3% 할인, 해외 이용금액 0.2% 할인",
                "기타": "[Weekly 할인 쿠폰] 매월 2회 국내 이용 할인 쿠폰 제공",
                "적립": "[Monthly 단골 적립] My Pick 가맹점 월 3, 6, 9번째 이용 건에 대해 마이신한포인트 1,000포인트 적립",
                "선택형": "카드 플레이트 선택 가능",
                "유의사항": "꼭 확인하세요!"
            },
            "카드 이미지": "card_image/check_card\\2492card.png"
        }
    },
    {
        "K-패스체크카드": {
            "혜택 요약": "대중교통 10% 적립, 생활서비스 1% 적립, KB Pay 이용 시 1% 추가 적립",
            "연회비 상세안내": "국내전용(Local) 없음 해외겸용(VISA) 없음",
            "주요 혜택": {
                "적립": "포인트리 적립 서비스",
                "유의사항": "꼭 확인하세요!"
            },
            "카드 이미지": "card_image/check_card\\2556card.png"
        }
    },
    {
        "신한 후불 기후동행 체크카드": {
            "혜택 요약": "온라인 5% 할인, 오프라인 5% 할인, ",
            "연회비 상세안내": "국내전용(Local) 없음 해외겸용(Mastercard) 없음",
            "주요 혜택": {
                "교통": "후불 기후동행카드 서비스 안내",
                "할인": "오프라인 5% 혜택",
                "유의사항": "꼭 확인하세요!"
            },
            "카드 이미지": "card_image/check_card\\2767card.png"
        }
    },
    {
        "나라사랑체크카드": {
            "혜택 요약": "P.X / GS25해군마트 최대 20% 할인, 대중교통 20% 할인, 영화 35% 할인",
            "연회비 상세안내": "국내전용 없음",
            "주요 혜택": {
                "기타": "군마트(P.X) 및 GS25 해군마트 환급할인군 KT공중전화 할인",
                "쇼핑": "GS홈쇼핑, CJ홈쇼핑, G마켓, 옥션 5% 환급할인",
                "대중교통": "대중교통(전국 버스/지하철) 20% 청구할인",
                "OTT/영화/문화": "CGV 35% / 스타벅스 20% / 아웃백, VIPS 20%/ 에버랜드, 롯데월드 현장예매 50% 환급할인",
                "교육/육아": "교보문고 5% 환급할인TOEIC, JPT 응시료 2,000원 환급할인",
                "통신": "이동통신 자동납부 2,500원 환급할인",
                "유의사항": "꼭 확인하세요!"
            },
            "카드 이미지": "card_image/check_card\\739card.png"
        }
    },
    {
        "위비트래블 체크카드": {
            "혜택 요약": "해외 5% 캐시백, 푸드 5% 캐시백, 해외 가맹점 이용 수수료 면제",
            "연회비 상세안내": "국내전용(Local) 없음 해외겸용(Mastercard) 없음",
            "주요 혜택": {
                "수수료우대": "해외 수수료 면제 서비스",
                "해외": "해외 5% 캐시백",
                "쇼핑": "쇼핑 5% 캐시백",
                "푸드": "푸드 5% 캐시백",
                "생활": "일상 5% 캐시백",
                "유의사항": "꼭 확인하세요!"
            },
            "카드 이미지": "card_image/check_card\\2700card.png"
        }
    },
    {
        "K-패스 삼성체크카드": {
            "혜택 요약": "대중교통 10% 캐시백, 이동통신 10% 캐시백, 편의점/커피전문점/제과 1,000원 캐시백",
            "연회비 상세안내": "국내전용(Local) 없음 해외겸용(mastercard) 없음",
            "주요 혜택": {
                "대중교통": "K-패스 마일리지",
                "통신": "이동통신 10% 캐시백",
                "편의점": "편의점/커피전문점/제과 1,000원 캐시벡",
                "영화": "CGV 3,000원 할인",
                "유의사항": "꼭 확인하세요!"
            },
            "카드 이미지": "card_image/check_card\\2563card.png"
        }
    },
    {
        "라이언 치즈 체크카드": {
            "혜택 요약": "커피 최대 1% 적립, 대중교통 1.5% 적립, 유튜브결제 5% 적립",
            "연회비 상세안내": "국내전용 없음 해외겸용(UnionPay) 없음",
            "주요 혜택": {
                "카페": "커피. 월~금 0.5% / 토,일 1% NH포인트 적립",
                "편의점": "편의점. 월~금 0.5% / 토,일 1% NH포인트 적립",
                "영화": "영화. 월~금 0.5% / 토,일 1% NH포인트 적립",
                "온라인쇼핑": "온라인쇼핑. 월~금 0.5% / 토,일 1% NH포인트 적립",
                "APP": "배달앱. 월~금 0.5% / 토,일 1% NH포인트 적립",
                "교통": "교통. 요일관계없이 1.5% NH포인트 적립",
                "해외": "해외. 요일관계없이 1.5% NH포인트 적립",
                "도서": "서점. 요일관계없이 1.5% NH포인트 적립",
                "생활": "자기계발, 공연·전시, H&B. 요일관계없이 1.5% NH포인트 적립",
                "기타": "유튜브, 넷플릭스, 유료 어플리케이션 결제 5% NH포인트 적립",
                "공항라운지": "국제공항 라운지 무료이용 서비스",
                "유의사항": "꼭 확인하세요!"
            },
            "카드 이미지": "card_image/check_card\\528card.png"
        }
    },
    {
        "케이뱅크 플러스 체크카드": {
            "혜택 요약": "모든가맹점 0.3% 캐시백, ATM수수료 무료 서비스, 언택트 업종 3% 특별캐시백",
            "연회비 상세안내": "헤외겸용(VISA) 없음",
            "주요 혜택": {
                "모든가맹점": "모든 가맹점에서 0.3% 캐시백",
                "기타": "최대 2만원 3% 특별 캐시백",
                "금융": "모든 은행, GS25 ATM 수수료 무료",
                "유의사항": "꼭 확인하세요!"
            },
            "카드 이미지": "card_image/check_card\\669card.png"
        }
    },
    {
        "올바른 NEW HAVE체크카드": {
            "혜택 요약": "국내외가맹점 0.2% 적립, 이용금액1위 3배 적립, 국제공항라운지 무료 아용",
            "연회비 상세안내": "국내전용(Local) 없음 해외겸용(mastercard) 없음",
            "주요 혜택": {
                "적립": "6개 영역 중 당월(1일~말일) 이용금액 1위/2위 영역은 기본적립의 3배/2배 자동적용",
                "공항라운지": "국제 공항라운지 무료이용 ",
                "금융": "농협 인터넷·모바일·스마트·텔레뱅킹 이체수수료 통합 월 5회 면제",
                "유의사항": "꼭 확인하세요! "
            },
            "카드 이미지": "card_image/check_card\\1765card.png"
        }
    },
    {
        "KB국민 기후동행체크카드": {
            "혜택 요약": "커피, 편의점, 약국, 패스트푸드 2% 할인, KB Pay, 올리브영 5% 할인, 영화 5% 할인",
            "연회비 상세안내": "국내전용(Local) 없음",
            "주요 혜택": {
                "교통": "후불 기후동행카드 안내",
                "할인": "할인 서비스",
                "유의사항": "꼭 확인하세요!"
            },
            "카드 이미지": "card_image/check_card\\2770card.png"
        }
    },
    {
        "K-패스(체크)": {
            "혜택 요약": "대중교통 건당 100원 할인, 커피 10% 할인, 쇼핑 10% 할인",
            "연회비 상세안내": "국내전용(Local) 없음 해외겸용(mastercard) 없음",
            "주요 혜택": {
                "대중교통": "대중교통 건당 100원 할인",
                "카페": "커피 10% 할인",
                "온라인쇼핑": "쇼핑 10% 할인",
                "편의점": "편의점 5% 할인",
                "영화": "영화 4천원 할인",
                "테마파크": "놀이공원 본인 무료입장 또는 자유이용권 최대 50% 할인",
                "금융": "금융우대서비스",
                "유의사항": "꼭 확인하세요!"
            },
            "카드 이미지": "card_image/check_card\\2526card.png"
        }
    },
    {
        "현대카드M CHECK": {
            "혜택 요약": "이용금액별 1~0.5% 적립, , ",
            "연회비 상세안내": "국내전용 2,000원\n\n* 후불교통카드 : 가능",
            "주요 혜택": {
                "적립": "업종·이용금액별 기본 M포인트 적립에 추가 M포인트 적립",
                "유의사항": "꼭 확인하세요!"
            },
            "카드 이미지": "card_image/check_card\\407card.png"
        }
    },
    {
        "K-패스 하나 체크카드": {
            "혜택 요약": "대중교통 10% 캐시백, 드럭스토어 1% 캐시백, 커피 1% 캐시백",
            "연회비 상세안내": "국내전용(Local) 없음 해외겸용(VISA) 없음",
            "주요 혜택": {
                "대중교통": "버스/지하철 10% 캐시백 (월 3천원, 월 6천원)",
                "드럭스토어": "다이소/올리브영 1% 캐시백 (월 1만원)",
                "카페": "스타벅스/커피빈 1% 캐시백 (월 5천원)",
                "유의사항": "꼭 확인하세요!"
            },
            "카드 이미지": "card_image/check_card\\2682card.png"
        }
    },
    {
        "가온 올포인트 체크카드": {
            "혜택 요약": "모든가맹점 0.2% 기본적립, 대형마트 0.8% 추가적립, GS칼텍스 0.8% 추가적립",
            "연회비 상세안내": "국내전용 없음 해외겸용(mastercard) 없음 * 후불교통카드 : 가능",
            "주요 혜택": {
                "모든가맹점": "국내외 가맹점 0.2% 포인트리 기본 적립",
                "카페/디저트": "커피/제과아이스크림 업종 0.2% 포인트리 추가 적립",
                "통신": "이동통신요금 자동이체 시 0.2% 포인트리 추가 적립",
                "편의점": "GS25 편의점 0.2% 포인트리 추가 적립",
                "교통": "대중교통(버스, 지하철), 택시 0.2% 포인트리 추가 적립",
                "대형마트": "대형마트 0.8% 포인트리 추가 적립",
                "주유": "GS칼텍스 주유소 0.8% 포인트리 추가 적립",
                "유의사항": "꼭 확인하세요!"
            },
            "카드 이미지": "card_image/check_card\\454card.png"
        }
    },
    {
        "올리 POINT 체크": {
            "혜택 요약": "국내외가맹점 0.2% 기본적립, 1~2위 이용영역 2~3배 적립, 공항라운지 무료 이용",
            "연회비 상세안내": "국내전용 없음 해외겸용(Master) 없음",
            "주요 혜택": {
                "적립": "아래 6개 영역 중 당월(1일~말일) 이용금액 1위/2위 영역은 기본적립의 3배/2배 자동적용",
                "공항라운지": "국제공항 라운지 무료이용",
                "유의사항": "꼭 확인하세요!"
            },
            "카드 이미지": "card_image/check_card\\676card.png"
        }
    },
    {
        "NH트래블리체크카드": {
            "혜택 요약": "해외가맹점 해외이용수수료 면제, 국내 가맹점 0.2~0.3% 캐시백 무제한, 일상 가맹점 0.6% 캐시백 무제한",
            "연회비 상세안내": "국내전용(Local) 없음 해외겸용(Mastercard) 없음",
            "주요 혜택": {
                "캐시백": "[국내 가맹점] 일상 가맹점 0.6% 캐시백",
                "해외": "[해외 서비스] 자동충전 서비스",
                "수수료우대": "[해외 서비스] 해외 이용 수수료 면제",
                "공항라운지": "[해외 서비스] 전 세계 공항라운지 본인 무료 입장 (The lounge / 더 라운지)"
            },
            "카드 이미지": "card_image/check_card\\2727_1card.png"
        }
    },
    {
        "카드의정석 EVERYDAY CHECK": {
            "혜택 요약": "국내/해외 가맹점 0.2% 적립, 우리페이 0.5% 추가 적립, 마트/슈퍼/커피/주유 1% 특별 적립",
            "연회비 상세안내": "국내전용(Local) 없음 해외겸용(Mastercard) 없음",
            "주요 혜택": {
                "국내외가맹점": "[기본 적립] 국내/해외 가맹점 0.2% 적립",
                "적립": "[특별 적립] 생활소비 1% 특별 적립",
                "유의사항": "꼭 확인하세요!"
            },
            "카드 이미지": "card_image/check_card\\2742card.png"
        }
    },
    {
        "기후동행카드(체크)": {
            "혜택 요약": "온라인쇼핑몰 5% 할인, 이동통신 자동납부 2,500원 할인, 커피 10% 할인",
            "연회비 상세안내": "국내전용(Local) 없음",
            "주요 혜택": {
                "쇼핑": "[온라인] 온라인 쇼핑몰 10% 청구할인",
                "도서": "[온라인] 온라인 서점 10% 청구할인",
                "교육/육아": "[온라인] 어학시험 10% 청구할인",
                "영화": "[온라인] CGV 온라인 예매(홈페이지, 모바일앱) 2,000원 청구할인",
                "배달앱": "[온라인] 배달앱(배달의 민족, 요기요) 3% 청구할인",
                "통신": "[오프라인] 이동통신 자동납부 2,500원 청구할인",
                "카페": "[오프라인] 커피(스타벅스, 이디야) 10% 청구할인",
                "편의점": "[오프라인] GS25 3% 청구할인",
                "테마파크": "[보너스 서비스] 놀이공원 할인 서비스",
                "교통": "후불 기후동행카드 이용 관련",
                "유의사항": "꼭 확인하세요!"
            },
            "카드 이미지": "card_image/check_card\\2773card.png"
        }
    },
    {
        "스타플러스 체크카드": {
            "혜택 요약": "커피·모바일·문화 10% 할인, 뷰티·편의점 5% 할인, 공항라운지 연 1회 제공",
            "연회비 상세안내": "국내전용(BC) 없음 해외겸용(mastercard) 없음",
            "주요 혜택": {
                "카페": "스타벅스, 커피빈 10% 할인",
                "게임": "구글플레이스토어, 앱스토어 10% 할인",
                "공연/전시": "인터파크 티켓 10% 할인",
                "드럭스토어": "올리브영, 미용실 업종 5% 할인",
                "편의점": "GS25, CU 5% 할인",
                "디지털구독": "넷플릭스, 유튜브프리미엄 1,000원 할인",
                "배달앱": "배달의 민족, 요기요 1,000원 할인",
                "통신": "SKT, KT, LG U+, Liiv M 2,500원 할인",
                "영화": "CGV 4,000원 할인",
                "테마파크": "에버랜드, 롯데월드 15,000원 할인",
                "해외이용": "해외 가맹점 2% 할인",
                "공항라운지": "공항라운지 더라운지멤버스",
                "유의사항": "꼭 확인하세요!"
            },
            "카드 이미지": "card_image/check_card\\2588card.png"
        }
    },
    {
        "트래블GO 체크카드": {
            "혜택 요약": "해외 가맹점 수수료 건당 $0.5 면제, 해외 ATM 인출 수수료 건당 $3 면제, 국내 가맹점 최대 5% 적립",
            "연회비 상세안내": "해외겸용(VISA) 없음",
            "주요 혜택": {
                "해외이용": "해외 가맹점 이용 수수료 면제 · 해외 ATM 인출 수수료 면제",
                "적립": "국내 가맹점 하나머니 적립 서비스",
                "유의사항": "꼭 확인하세요!"
            },
            "카드 이미지": "card_image/check_card\\2740card_1.png"
        }
    },
    {
        "카카오페이 체크카드": {
            "혜택 요약": "카카오페이 15% 할인, 편의점 5% 할인, 온라인쇼핑 10% 할인",
            "연회비 상세안내": "국내전용 없음",
            "주요 혜택": {
                "카카오페이": "카카오페이 15% 할인",
                "편의점": "편의점 5% 할인",
                "온라인쇼핑": "온라인쇼핑 10% 할인",
                "기타": "어학시험 2천원 할인",
                "영화": "영화 2천원 할인",
                "카페": "커피 10% 할인",
                "패스트푸드": "패스트푸드 10% 할인",
                "유의사항": "꼭 확인하세요!"
            },
            "카드 이미지": "card_image/check_card\\2094card.png"
        }
    },
    {
        "신한카드 주거래 체크": {
            "혜택 요약": "전가맹점 0.3% 적립, 쇼핑, 해외가맹점 0.7% 추가적립, 생활가맹점 1.7% 추가적립",
            "연회비 상세안내": "해외겸용(VISA, UnionPay) 없음\n* 후불교통카드 : 지원",
            "주요 혜택": {
                "모든가맹점": "모든 가맹점 0.3% 포인트 적립",
                "쇼핑": "신한은행 결제 계좌 연결 제공 서비스(추가 포인트 적립)",
                "은행사": "주거래Package",
                "유의사항": "꼭 확인하세요!"
            },
            "카드 이미지": "card_image/check_card\\284card.png"
        }
    },
    {
        "하나 기후동행체크카드": {
            "혜택 요약": "편의점 1,000원 캐시백, 서점 1,000원 캐시백, 베이커리 1,000원 캐시백",
            "연회비 상세안내": "국내전용(Local) 없음",
            "주요 혜택": {
                "캐시백": "캐시백 서비스",
                "교통": "후불교통 기능 이용안내",
                "유의사항": "꼭 확인하세요!"
            },
            "카드 이미지": "card_image/check_card\\2768card.png"
        }
    },
    {
        "IBK무민카드(체크)": {
            "혜택 요약": "대중교통 건당100원 할인, 온라인쇼핑 10% 할인, 커피전문점 10% 할인",
            "연회비 상세안내": "국내전용(BC) 없음 해외겸용(UnionPay) 없음",
            "주요 혜택": {
                "대중교통": "버스, 지하철 이용건당 100원 할인",
                "소셜커머스": "쿠팡, 티몬, 위메프 10% 할인",
                "편의점": "GS25, CU, 세븐일레븐, 올리브영 5% 할인",
                "영화": "CGV, 롯데시네마, 메가박스 4천원 할인",
                "카페": "주요 커피전문점 10% 할인",
                "금융": "금융우대서비스",
                "테마파크": "주요 놀이공원 무료입장 또는 입장료/자유이용권 할인 (월 1회, 연 2회)",
                "유의사항": "꼭 확인하세요!"
            },
            "카드 이미지": "card_image/check_card\\674card.png"
        }
    },
    {
        "신한카드 Pick E 체크": {
            "혜택 요약": "편의점·커피 10% 적립, 사진·볼링·테니스·스키 10% 적립, One Pick 맛집 3천 포인트 적립",
            "연회비 상세안내": "국내전용(Local) 없음 해외겸용(mastercard) 없음",
            "주요 혜택": {
                "편의점": "4대 편의점 이용 시 10% 적립",
                "카페": "커피 업종 이용 시 10% 적립",
                "해외이용": "해외 이용금액 1% 적립",
                "생활": "놀이 영역 이용 시 10% 적립",
                "푸드": "One Pick 맛집 가맹점 최대 3천 포인트 적립",
                "유의사항": "꼭 확인하세요!"
            },
            "카드 이미지": "card_image/check_card\\2528card.png"
        }
    },
    {
        "NH 무럭이 체크카드": {
            "혜택 요약": "전가맹점 0.2% 적립, 쇼핑 0.2~0.4% 적립, 국제공항 라운지 무료 이용",
            "연회비 상세안내": "국내전용(Local) 없음 *VISA브랜드의 경우 11/20(월)부터 신청 가능합니다.",
            "주요 혜택": {
                "국내외가맹점": "[기본 적립] 국내/외 이용가맹점 0.2% NH포인트 적립",
                "적립": "[스마트 적립] 6개 영역 중 이용금액 1위/2위 영역 기본적립의 3배/2배 적립",
                "공항라운지": "국제공항 라운지 무료이용"
            },
            "카드 이미지": "card_image/check_card\\2620card.png"
        }
    },
    {
        "카카오페이 체크카드": {
            "혜택 요약": "카카오페이 7% 캐시백, 대중교통 5% 캐시백, 스타벅스 5% 캐시백",
            "연회비 상세안내": "해외겸용(VISA) 없음 * 후불교통카드 : 가능",
            "주요 혜택": {
                "캐시백": "카카오페이, 통신요금자동이체, 커피, 대중교통 캐시백",
                "선택형": "카드플레이트 디자인 선택 가능",
                "유의사항": "꼭 확인하세요!"
            },
            "카드 이미지": "card_image/check_card\\382card.png"
        }
    },
    {
        "그랑블루 체크카드": {
            "혜택 요약": "모아포인트 0.3~1.0% 적립, 기프트바우처 연1회 제공, 공항라운지 무료 이용",
            "연회비 상세안내": "해외겸용(BC Global) 95,000원 (기본 5,000원 + 제휴 90,000원) 해외겸용(mastercard) 100,000원 (기본 5,000원 + 제휴 95,000원) ※ 해당 카드 연회비(기본 연회비 + 제휴 연회비)는 카드별로 청구됩니다. *후불교통카드 발급가능",
            "주요 혜택": {
                "바우처": "GIFT VOUCHER (연 1회, 택1회)",
                "모든가맹점": "사용업종 또는 결제건당 금액에 따라 0.3~1% 모아포인트 적립",
                "공항라운지/PP": "체크 브랜드별 공항라운지 이용 서비스",
                "여행/숙박": "[Travel Service] 국내외 여행 관련 서비스 제공",
                "푸드": "치킨, 피자 10% 청구할인",
                "영화": "전국 영화관 3,000원 청구할인",
                "레저/스포츠": "골프 우대 서비스 및 자전거 무료 세척 서비스",
                "주유소": "SK주유 및 충전 시 리터당 60원 청구할인 ",
                "유의사항": "꼭 확인하세요!"
            },
            "카드 이미지": "card_image/check_card\\325card.png"
        }
    },
    {
        "IBK 나라사랑카드": {
            "혜택 요약": "대중교통 10% 할인, 철도/고속버스 5% 할인, CU 5% 현장할인",
            "연회비 상세안내": "국내전용(BC) 없음",
            "주요 혜택": {
                "교통": "전국 시내버스/지하철, KTX(철도)/SRT/고속버스 할인",
                "통신": "군 공중전화요금 자동이체 시 10% 할인",
                "편의점": "CU 및 군마트(PX)할인",
                "화장품": "이니스프리 온/오프라인 매장 상시 10% 할인",
                "영화": "CGV 3천원 현장할인(동반1인 포함 시)",
                "패밀리레스토랑": "아웃백스테이크 20% 현장할인",
                "테마파크": "주요 놀이공원 본인 자유이용권 50% 현장할인",
                "여행/숙박": "여기어때 결제금액 매월 최대 1만원 청구할인",
                "도서": "인터넷 토익시험 접수(결제) 및 온라인서적(교보문고) 구매시 2천원 청구할인",
                "은행사": "군 복무 중 은행 ATM 출금수수료 무제한 면제",
                "멤버십포인트": "그린카드 멤버십 서비스 및 Syrup 통합 멤버십 서비스",
                "유의사항": "꼭 확인하세요!"
            },
            "카드 이미지": "card_image/check_card\\446card.png"
        }
    },
    {
        "삼성체크카드 & CASHBACK": {
            "혜택 요약": "0.6~0.2% 캐시백 제공, 놀이공원 50% 할인, CGV 3,000원 할인",
            "연회비 상세안내": "국내전용 없음 / *후불교통카드: 가능",
            "주요 혜택": {
                "모든가맹점": "업종 및 연간 이용금액에 따라 0.2%~0.6% 캐시백",
                "영화": "CGV 3,000원 할인",
                "테마파크": "놀이공원 자유이용권 50%·워터파크 입장권 30% 현장할인",
                "유의사항": "꼭 확인하세요!"
            },
            "카드 이미지": "card_image/check_card\\394card.png"
        }
    },
    {
        "어피치 스윗 체크카드": {
            "혜택 요약": "온라인 간편결제 3% 할인, 카페 4% 할인, 넷플릭스 5% 할인",
            "연회비 상세안내": "국내전용 없음 해외겸용(UnionPay) 없음",
            "주요 혜택": {
                "간편결제": "올원페이, 카카오페이, 삼성페이 온라인결제 3% 할인",
                "카페": "스타벅스, 투썸플레이스, 커피빈 4% 할인",
                "화장품": "올리브영, 랄라블라 4% 할인",
                "기타": "유튜브프리미엄, 넷플릭스, 유료 어플리케이션 5% 할인",
                "공항라운지": "국제공항 라운지 무료이용 서비스",
                "유의사항": "꼭 확인하세요!"
            },
            "카드 이미지": "card_image/check_card\\586card.png"
        }
    },
    {
        "KB국민 우리동네 체크카드": {
            "혜택 요약": "세탁소, 정육점 10% 할인, 슈퍼마켓 5% 할인, 번개장터 5% 할인",
            "연회비 상세안내": "국내전용(Local) 없음 해외겸용(VISA, UnionPay)없음",
            "주요 혜택": {
                "생활": "세탁소 10% 할인",
                "기타": "번개장터(번개페이) 5% 할인",
                "SSM": "슈퍼마켓 5% 할인",
                "선택형": "카드 디자인 선택 가능",
                "유의사항": "꼭 확인하세요!"
            },
            "카드 이미지": "card_image/check_card\\2332card.png"
        }
    },
    {
        "able Premier Members 카드": {
            "혜택 요약": "한도없이 0.5% 캐시백, 호텔 최대 50% 할인, ",
            "연회비 상세안내": "국내전용 없음 * 멤버십 고객 전용카드",
            "주요 혜택": {
                "할인": "현장할인서비스높은 할인율과 다양한 제휴처!",
                "금융": "able 금융서비스언제 어디서나 수수료 면제!"
            },
            "카드 이미지": "card_image/check_card\\2225card.png"
        }
    },
    {
        "행복한 체크카드": {
            "혜택 요약": "마트 10% 캐시백, 병·의원/약국 10% 캐시백, 학원 10% 캐시백",
            "연회비 상세안내": "해외겸용(MASTER) 없음",
            "주요 혜택": {
                "병원/약국": "병원·의원, 모든 약국 10% 캐시백",
                "학원": "학원 10% 캐시백",
                "대형마트": "마트 10% 캐시백",
                "공연/전시": "문화 10% 캐시백",
                "기타": "순수 우편서비스 12% · 우체국쇼핑 10% 캐시백지자체 시설 무료입장 및 할인, 에코머니 적립 등",
                "유의사항": "꼭 확인하세요!"
            },
            "카드 이미지": "card_image/check_card\\585card.png"
        }
    },
    {
        "스타체크카드": {
            "혜택 요약": "GS칼텍스 60~50원/L  할인, CGV 3,000원 할인, 이동통신요금 2,500원 할인",
            "연회비 상세안내": "국내전용 없음 해외겸용(VISA, mastercard) 없음 * 후불교통카드 : 가능",
            "주요 혜택": {
                "주유소": "GS칼텍스 리터당 주중 50원, 주말 60원 환급할인",
                "대중교통": "버스·지하철 5% 청구할인",
                "통신": "이동통신요금 2,500원 환급할인",
                "영화": "CGV 3,000원 환급할인",
                "테마파크": "에버랜드 50% 환급할인",
                "온라인쇼핑": "G마켓·옥션 3% 환급할인",
                "드럭스토어": "올리브영 5% 환급할인",
                "도서": "교보문고 3% 환급할인",
                "패밀리레스토랑": "아웃백·VIPS 10% 환급할인",
                "기타": "통합할인한도",
                "유의사항": "꼭 확인하세요!"
            },
            "카드 이미지": "card_image/check_card\\351card.png"
        }
    },
    {
        "영리한 PLUS 체크카드": {
            "혜택 요약": "디지털콘텐츠 20% 캐시백, 온라인쇼핑 15% 캐시백, 배달앱 15% 캐시백",
            "연회비 상세안내": "해외겸용(Mastercard) 없음",
            "주요 혜택": {
                "디지털구독": "유튜브프리미엄, 넷플릭스, 웨이브, 티빙, 멜론, 지니 20% 캐시백",
                "온라인쇼핑": "11번가, G마켓, 옥션, 쿠팡, 위메프, 티몬 15% 캐시백",
                "배달앱": "배달의민족, 요기요, 쿠팡이츠 15% 캐시백",
                "카페": "스타벅스, 투썸플레이스, 이디야 5% 캐시백",
                "생활": "올리브영, 랄라블라, 다이소, GS25, CU, 이마트24 5% 캐시백",
                "기타": "우편요금, 인터넷우체국, 우체국쇼핑, EMS 5% 캐시백",
                "유의사항": "꼭 확인하세요!"
            },
            "카드 이미지": "card_image/check_card\\2227card.png"
        }
    },
    {
        "미래에셋증권 체크카드(할인 2)": {
            "혜택 요약": "커피전문점 10% 할인, 편의점 10% 할인, 디지털구독 건당 5,000원 할인",
            "연회비 상세안내": "국내전용 없음",
            "주요 혜택": {
                "카페": "커피전문점 10% 할인",
                "마트/편의점": "편의점 10% 할인마트 5% 할인",
                "디지털구독": "디지털구독 10% 할인",
                "유의사항": "꼭 확인하세요!"
            },
            "카드 이미지": "card_image/check_card\\2216card.png"
        }
    },
    {
        "신한카드 Global Air 스카이패스 체크": {
            "혜택 요약": "주중 3,000원 당 1마일리지 적립, 주말 1,500원 당 1마일리지 적립, 해외인출 1건당 US $3 캐시백",
            "연회비 상세안내": "국내전용 10,000원 해외겸용(VISA) 10,000원",
            "주요 혜택": {
                "대한항공": "마일리지 적립 서비스",
                "해외이용": "해외 인출 1건당 US $3 캐시백 제공",
                "프리미엄 서비스": "VISA 플래티늄 서비스 제공",
                "유의사항": "꼭 확인하세요!"
            },
            "카드 이미지": "card_image/check_card\\642card.png"
        }
    },
    {
        "카카오페이 트래블로그 체크카드": {
            "혜택 요약": "카카오페이포인트 최대 10% 적립, 해외 가맹점 이용수수료 면제, 해외 ATM 인출수수료 면제",
            "연회비 상세안내": "국내전용(Local) 없음 해외겸용(Mastercard) 없음",
            "주요 혜택": {
                "적립": "국내 가맹점 카카오페이 포인트 적립 서비스",
                "해외이용": "해외 이용수수료 면제 서비스",
                "유의사항": "꼭 확인하세요!"
            },
            "카드 이미지": "card_image/check_card\\2775card.png"
        }
    },
    {
        "신한카드 Pick I 체크": {
            "혜택 요약": "편의점·커피 10% 적립, 디지털 구독 10% 적립, One Pick 쇼핑몰 3천 포인트 적립",
            "연회비 상세안내": "국내전용(Local) 없음 해외겸용(Mastercard) 없음",
            "주요 혜택": {
                "편의점": "4대 편의점 이용 시 10% 적립",
                "카페": "커피 업종 이용 시 10% 적립",
                "해외이용": "해외 이용금액 1% 적립",
                "디지털구독": "디지털 구독 영역 이용 시 10% 적립",
                "온라인쇼핑": "One Pick 온라인 쇼핑몰 가맹점 최대 3천 포인트 적립",
                "유의사항": "꼭 확인하세요!"
            },
            "카드 이미지": "card_image/check_card\\2527card.png"
        }
    },
    {
        "민 체크카드": {
            "혜택 요약": "대형마트 5% 할인, SK에너지 60원/L 할인, 대중교통 5% 할인",
            "연회비 상세안내": "국내전용 없음 해외겸용(VISA, mastercard) 없음 *후불교통카드 발급가능",
            "주요 혜택": {
                "대형마트": "이마트·롯데마트·홈플러스 5% 환급할인",
                "주유소": "SK에너지 리터당 60원 환급할인",
                "정비": "스피드메이트 엔진오일교환 2만원 현장할인 및 정비 할인",
                "패스트푸드": "패스트푸드 10% 환급할인",
                "통신": "이동통신요금 2,500원 환급할인",
                "대중교통": "버스·지하철 5% 청구할인",
                "편의점": "CU편의점 3% CU포인트 적립",
                "기타": "통합할인한도",
                "유의사항": "꼭 확인하세요!"
            },
            "카드 이미지": "card_image/check_card\\346card.png"
        }
    },
    {
        "더담은 체크카드": {
            "혜택 요약": "교육 2천원 할인, 주유 1천원 할인, 음식점 1천원 할인",
            "연회비 상세안내": "국내전용(Local) 없음 해외겸용(VISA)",
            "주요 혜택": {
                "학원": "대상가맹점 결제 시 2천원 할인",
                "주유": "전국 주유소 및 충전소, 전기차충전소 결제 시 1천원 할인캐시백",
                "일반음식점": "음식점 업종 결제 시 1천원 할인캐시백",
                "쇼핑": "대상가맹점 결제 시 1천원 할인",
                "편의점": "GS25, CU, 세븐일레븐, 이마트24 결제 시 500원 할인캐시백",
                "해외": "해외 서비스수수료, 현금(예금)인출수수료, 예금잔액조회수수료 면제",
                "유의사항": "꼭 확인하세요!"
            },
            "카드 이미지": "card_image/check_card\\2745card.png"
        }
    },
    {
        "카드의정석 DON CHECK": {
            "혜택 요약": "편의점, 배달의민족 5% 적립, 쿠팡, 무신사 5% 적립, 구글 Play스토어, 애플 APP Store 5% 적립",
            "연회비 상세안내": "국내전용(Local) 없음 해외겸용(mastercard) 없음",
            "주요 혜택": {
                "푸드": "[DO EAT] 편의점, 배달의민족 5% 적립",
                "쇼핑": "[DO BUY] 쿠팡, 무신사 5% 적립",
                "게임": "[DO PLAY] 구글 Play스토어, 애플 APP Store 5% 적립",
                "유의사항": "꼭 확인하세요!"
            },
            "카드 이미지": "card_image/check_card\\2639card.png"
        }
    },
    {
        "위글위글 첵첵 체크카드": {
            "혜택 요약": "네이버페이,카카오페이 2~4천원 할인, 스타벅스 2~4천원 할인, 텐바이텐 2~4천원 할인",
            "연회비 상세안내": "국내전용 없음 해외겸용(VISA) 없음",
            "주요 혜택": {
                "간편결제": "네이버페이.카카오페이.SSG페이 최대 4천원 할인 ",
                "대중교통": "버스.지하철 최대 4천원 할인",
                "편의점": "CU편의점 최대 4천원 할인",
                "카페": "스타벅스(사이렌오더 포함) 최대 4천원 할인",
                "영화": "CGV 최대 4천원 할인",
                "기타": "텐바이텐 최대 4천원 할인",
                "드럭스토어": "올리브영,안경(렌즈)점 최대 4천원 할인",
                "도서": "YES24, 교보문고 최대 4천원 할인",
                "공연/전시": "인터파크티켓 최대 4천원 할인",
                "유의사항": "꼭 확인하세요!"
            },
            "카드 이미지": "card_image/check_card\\614card.png"
        }
    },
    {
        "현대카드M HYBRID": {
            "혜택 요약": "이용금액별 1~0.5% 적립, , ",
            "연회비 상세안내": "국내전용 없음\n\n* 연간 300만원 이상 이용 시 차년도 연회비 면제(일시불 이용금액 기준)",
            "주요 혜택": {
                "모든가맹점": "당월 이용금액별 M포인트 적립",
                "하이브리드": "체크결제와 신용결제 서비스를 한번에",
                "유의사항": "꼭 확인하세요!"
            },
            "카드 이미지": "card_image/check_card\\414card.png"
        }
    },
    {
        "노리2 체크카드(Play)": {
            "혜택 요약": "커피·모바일·문화 10% 할인, 뷰티·편의점 5% 할인, 에버랜드·롯데월드 15,000원 할인",
            "연회비 상세안내": "국내전용(Local) 없음 해외겸용(Mastercard) 없음",
            "주요 혜택": {
                "카페": "[일상] 스타벅스, 커피빈 10% 할인",
                "게임": "[Play] PC방 업종 10% 할인",
                "공연/전시": "[일상] 인터파크 티켓 10% 할인",
                "헤어": "[일상] 올리브영, 미용실 업종 5% 할인",
                "편의점": "[일상] GS25, CU 5% 할인",
                "디지털구독": "[일상] 넷플릭스, 유튜브프리미엄 1,000원 할인",
                "배달앱": "[일상] 배달의민족, 요기요 1,000원 할인",
                "통신": "[일상] SKT, KT, LG U+, Liiv M 2,500원 할인",
                "영화": "[일상] CGV 4,000원 할인",
                "테마파크": "[일상] 에버랜드, 롯데월드 15,000원 할인",
                "패스트푸드": "[Play] 패스트푸드 업종 1,000원 할인",
                "유의사항": "꼭 확인하세요!"
            },
            "카드 이미지": "card_image/check_card\\2550card.png"
        }
    },
    {
        "체크카드": {
            "혜택 요약": "농협판매장 5% 적립, 주유소 40원/L 할인, 영화 10% 할인",
            "연회비 상세안내": "국내전용 없음 해외겸용(Master) 없음",
            "주요 혜택": {
                "적립": "농협판매장 NH포인트 적립",
                "주유": "농협운영주유소, GS칼텍스 적립 및 할인",
                "OTT/영화/문화": "문화서비스 할인",
                "수수료우대": "외화 환전 우대 서비스",
                "생활": "기타 서비스",
                "유의사항": "꼭 확인하세요!"
            },
            "카드 이미지": "card_image/check_card\\499card.png"
        }
    },
    {
        "신한 슈퍼SOL 체크": {
            "혜택 요약": "모든가맹점 0.3% 적립, 생활가맹점 총 2% 적립, 쇼핑/해외 총 1% 적립",
            "연회비 상세안내": "국내전용 없음 해외겸용(MASTER) 없음",
            "주요 혜택": {
                "모든가맹점": "모든 가맹점 0.3% 포인트 적립",
                "생활": "생활가맹점 총 2% 포인트 적립 (기본 0.3%+추가 1.7%)",
                "쇼핑": "쇼핑가맹점 총 1% 포인트 적립(기본 0.3%+추가 0.7%)",
                "해외이용": "해외 가맹점 이용금액 총 1% 포인트 적립(기본 0.3%+추가 0.7%)",
                "유의사항": "꼭 확인하세요!"
            },
            "카드 이미지": "card_image/check_card\\638card.png"
        }
    },
    {
        "카카오뱅크 개인사업자 체크카드": {
            "혜택 요약": "생활업종 0.3% 캐시백, 사업업종 3% 캐시백, ",
            "연회비 상세안내": "국내전용(Local) 없음 해외겸용(mastercard)없음 *발급수수료 2,000원(분실/훼손에 따른 재발급 시에만 부과)",
            "주요 혜택": {
                "생활": "매일 가는 곳은 혜택 고민 없이 0.3% 캐시백",
                "비즈니스": "사업운영에 꼭 필요한 곳에서 3% 캐시백",
                "유의사항": "꼭 확인하세요!"
            },
            "카드 이미지": "card_image/check_card\\2421card.png"
        }
    },
    {
        "카드의정석 APT CHECK": {
            "혜택 요약": "아파트관리비 최대1만원 캐시백, 유튜브정기권 30% 캐시백, ",
            "연회비 상세안내": "국내전용(BC) 9,000원 해외겸용(MasterCard) 9,000원",
            "주요 혜택": {
                "공과금": "아파트관리비(공공 임대료) 3천~10천원 캐시백",
                "기타": "유튜브 프리미엄 정기권 30% 캐시백",
                "유의사항": "꼭 확인하세요!"
            },
            "카드 이미지": "card_image/check_card\\545card.png"
        }
    },
    {
        "FANtastic S 신한카드 체크": {
            "혜택 요약": "간편결제(FAN페이) 15% 캐시백, 쿠팡,티몬 10% 캐시백, 스타벅스 10% 캐시백",
            "연회비 상세안내": "해외겸용(mastercard) 없음 * 후불교통카드 : 지원",
            "주요 혜택": {
                "간편결제": "간편결제(FAN페이) 15% 캐시백",
                "소셜커머스": "소셜커머스(쿠팡,티몬) 10% 캐시백",
                "편의점": "편의점(CU) 10% 캐시백",
                "카페": "커피(스타벅스) 10% 캐시백",
                "해외이용": "해외 전 가맹점 이용액(온라인 포함) 1.2% 캐시백해외인출 1건당 US $3 캐시백",
                "캐시백": "통합캐시백한도",
                "유의사항": "꼭 확인하세요!"
            },
            "카드 이미지": "card_image/check_card\\278card.png"
        }
    },
    {
        "당근머니 하나 체크카드": {
            "혜택 요약": "지역 가맹점 3.0% 적립, 당근 앱 내 결제 5.0% 적립, 국내 전 가맹점 0.5% 적립",
            "연회비 상세안내": "국내전용(Local) 없음 해외겸용(Mastercard) 없음",
            "주요 혜택": {
                "적립": "당근머니 적립 서비스",
                "유의사항": "꼭 확인하세요!"
            },
            "카드 이미지": "card_image/check_card\\2720card_1.png"
        }
    },
    {
        "트래블페이 충전카드": {
            "혜택 요약": "주요 통화 무료 환전수수료, 해외결제 0% 수수료, 충전가능외화 31개 선충전",
            "연회비 상세안내": "해외겸용(VISA) 없음",
            "주요 혜택": {
                "간편결제": "트래블페이: 31개 외화를 미리 충전하고, 수수료 없이 해외결제",
                "수수료우대": "카드 하나에 모든 외화 충전VISA 가맹점에서 수수료 없이 카드 결제 가능",
                "해외이용": "원하는 시점, 원하는 환율에 외화 충전 / 환전주요 통화는 환전 수수료 무료, 기타 통화는 환전 수수료 0.5% ~ 2.5%로 국내 최저",
                "해외직구": "해외직구 수수료 무료로 직구 / 현지결제"
            },
            "카드 이미지": "card_image/check_card\\2320card.png"
        }
    },
    {
        "롯데체크카드": {
            "혜택 요약": "전국 가맹점 0.2% L.POINT 적립, SK주유소 50P/L 주유포인트 적립, ",
            "연회비 상세안내": "국내전용 없음\n해외겸용(VISA) 없음",
            "주요 혜택": {
                "적립": "전국 가맹점 및 SK주유소 이용 시 적립혜택",
                "해외": "해외이용 안내",
                "유의사항": "꼭 확인하세요!"
            },
            "카드 이미지": "card_image/check_card\\403card.png"
        }
    },
    {
        "NH올원체크카드": {
            "혜택 요약": "실적관계없이 0.4~0.2% 적립, 해외이용액 0.4% 적립, OK캐시백 포인트 적립",
            "연회비 상세안내": "해외겸용(mastercard) 없음 * 후불교통카드 : 가능",
            "주요 혜택": {
                "적립": "전월실적에 상관없이 0.2 ~ 0.4% 적립",
                "OK캐쉬백": "제휴멤버십 서비스",
                "기타": "기타서비스",
                "유의사항": "꼭 확인하세요!"
            },
            "카드 이미지": "card_image/check_card\\368card.jpg"
        }
    },
    {
        "카카오뱅크 mini카드": {
            "혜택 요약": "전국ATM 수수료 무료 서비스, CU에서는 현금없이 T머니충전, ",
            "연회비 상세안내": "국내전용 없음",
            "주요 혜택": {
                "온라인쇼핑": "오프라인은 물론 온라인에서도 결제",
                "대중교통": "CU에서는 현금없이 카드로 티머니 간편충전!",
                "기타": "전국 ATM 어디서나 수수료 무료!",
                "유의사항": "꼭 확인하세요!"
            },
            "카드 이미지": "card_image/check_card\\686card.png"
        }
    },
    {
        "카카오페이카드3": {
            "혜택 요약": "MZ라이프팩 최대 4만 포인트 적립, 어디서나적립팩 최대 0.4% 적립, ",
            "연회비 상세안내": "해외겸용 없음(스카이패스 카드 제외)",
            "주요 혜택": {
                "생활": "[MZ 라이프팩] 최대 40,000P 적립(2023.7.1~2023.12.31)",
                "적립": "[어디서나 적립팩] 국내 모든 가맹점에서 최대 0.4% 적립(2023.7.1 ~ 2023.12.31)",
                "기타": "전국 편의점, 지하철 ATM 수수료 무료",
                "선택형": "마음에 드는 카드를 선택하세요",
                "유의사항": "꼭 확인하세요!"
            },
            "카드 이미지": "card_image/check_card\\2303card.png"
        }
    },
    {
        "일상의 기쁨카드(체크)": {
            "혜택 요약": "버스/지하철 건당 100원 할인, 편의점 5% 할인, 영화 4,000원 할인",
            "연회비 상세안내": "해외겸용(mastercard, UnionPay) 없음",
            "주요 혜택": {
                "대중교통": "버스, 지하철 이용건당 100원 할인",
                "편의점": "GS25, CU, 세븐일레븐 5% 할인",
                "드럭스토어": "올리브영 5% 할인",
                "소셜커머스": "쿠팡, 티켓몬스터, 위메프 10% 할인",
                "영화": "CGV, 롯데시네마, 메가박스 4천원 할인",
                "카페": "주요 커피전문점 10% 할인",
                "은행사": "금융우대서비스",
                "테마파크": "주요 놀이공원 무료입장 또는 입장료/자유이용권 할인",
                "기타": "통합할인한도",
                "유의사항": "꼭 확인하세요!"
            },
            "카드 이미지": "card_image/check_card\\441card.png"
        }
    },
    {
        "IBK 무직타이거 카드(체크)": {
            "혜택 요약": "버스,지하철 건당 100원 할인, 온라인쇼핑 10% 할인, 편의점 5% 할인",
            "연회비 상세안내": "국내전용(BC) 없음 해외겸용(Unionpay) 없음",
            "주요 혜택": {
                "대중교통": "버스, 지하철 이용건당 100원 할인",
                "편의점": "GS25, CU, 세븐일레븐, 올리브영 5% 할인",
                "온라인쇼핑": "쿠팡, 티몬, 위메프 10% 할인",
                "영화": "CGV, 메가박스, 롯데시네마 4천원 할인",
                "카페": "주요 커피전문점 10% 할인",
                "금융": "금융우대서비스(결제계좌를 IBK 기업은행 입출식 통장으로 이용 시)",
                "테마파크": "놀이공원 최대 50% 할인 (월 1회, 연 2회 제공)",
                "유의사항": "꼭 확인하세요!"
            },
            "카드 이미지": "card_image/check_card\\1490card.png"
        }
    },
    {
        "DC줌체크카드(비씨)": {
            "혜택 요약": "온라인쇼핑 10% 할인, 커피 10% 할인, 대중교통 10% 할인",
            "연회비 상세안내": "해외겸용(UnionPay) 없음 * 후불교통카드 : 가능",
            "주요 혜택": {
                "대중교통": "대중교통(버스, 지하철) 10% 청구할인",
                "카페": "주요 커피 전문점 10% 청구할인",
                "온라인쇼핑": "주요 온라인쇼핑몰·소셜커머스 10% 청구할인",
                "패밀리레스토랑": "주요 패밀리레스토랑 10% 청구할인",
                "도서": "주요 서점 10% 청구할인",
                "병원": "전국 병원·약국 10% 청구할인",
                "영화": "전국 주요 영화관 1,500원 청구할인",
                "금융": "SMS 휴대폰 바로알림 서비스",
                "기타": "통합할인한도",
                "유의사항": "꼭 확인하세요!"
            },
            "카드 이미지": "card_image/check_card\\365card.png"
        }
    },
    {
        "신한카드 S-Line 체크(마이펫)": {
            "혜택 요약": "모든가맹점 0.2~0.5% 적립, 요식업종 5% 할인, 대중교통 5% 할인",
            "연회비 상세안내": "국내전용 없음 해외겸용(VISA) 없음",
            "주요 혜택": {
                "모든가맹점": "전 가맹점 이용금액의 0.2% ~ 0.5% 마이신한포인트 적립",
                "푸드": "요식업종 이용금액의 5% 할인",
                "교통": "버스, 지하철 이용금액의 5% 할인(후불교통 카드 선택 시)SK주유소 주유 시 리터당 40원 할인(후불교통카드 미 선택 시)",
                "쇼핑": "홈쇼핑 이용금액의 5% 할인해외 이용금액의 5% 할인",
                "금융": "금융 우대 서비스",
                "유의사항": "꼭 확인하세요!"
            },
            "카드 이미지": "card_image/check_card\\647card.png"
        }
    },
    {
        "가온체크카드": {
            "혜택 요약": "모든가맹점 0.2% 적립, 주말/공휴일 0.2% 추가적립, 대중교통/택시 0.2% 추가적립",
            "연회비 상세안내": "국내전용 없음 해외겸용(mastercard) 없음 * 후불교통카드 발급가능",
            "주요 혜택": {
                "모든가맹점": "모든 가맹점 포인트리 기본적립",
                "푸드": "음식점, 커피전문점 업종 포인트리 추가적립",
                "교통": "대중교통, 택시 포인트리 추가적립",
                "통신": "이동통신요금 포인트리 추가적립",
                "유의사항": "꼭 확인하세요!"
            },
            "카드 이미지": "card_image/check_card\\336card.png"
        }
    },
    {
        "내일배움체크카드": {
            "혜택 요약": "주유소 40원/L 할인, 서적 10% 할인, 커피 10% 할인",
            "연회비 상세안내": "국내전용 없음 / 후불교통카드: 불가",
            "주요 혜택": {
                "교육/육아": "내일배움카드제도란?",
                "주유소": "농협운영주유소, NH-Oil 및 GS칼텍스 주유소 할인 또는 적립",
                "대형마트": "농협판매장 5% NH포인트 적립",
                "영화": "문화 서비스(영화, 커피, 서적) 10% 청구 할인",
                "여행/숙박": "국내·외 여행스케치 현장 할인(3~5%)",
                "유의사항": "꼭 확인하세요!"
            },
            "카드 이미지": "card_image/check_card\\367card.png"
        }
    },
    {
        "SC제일은행-현대카드 M CHECK": {
            "혜택 요약": "월 100만원 미만 이용 시 0.5% M포인트 적립, 월 100만원 이상 이용 시 1% M포인트 적립, 전국 CD·ATM 현금 인출 가능",
            "연회비 상세안내": "국내전용(Local) 없음 해외겸용(VISA) 없음",
            "주요 혜택": {
                "적립": "M포인트 적립",
                "금융": "SC제일은행 혜택",
                "기타": "M포인트 사용",
                "유의사항": "꼭 확인하세요!"
            },
            "카드 이미지": "card_image/check_card\\2430card.png"
        }
    },
    {
        "케이뱅크 X KT멤버십더블혜택 체크카드": {
            "혜택 요약": "KT통신요금 20~5% 캐시백, KT멤버십 더블 할인, 해외이용 수수료 면제",
            "연회비 상세안내": "해외겸용(VISA) 없음\n\n신청조건: KT상품가입자",
            "주요 혜택": {
                "KT": "KT통신요금 5~20%캐시백",
                "멤버십포인트": "KT멤버십 제휴가맹점 할인, POP CARD 할인 및 GS&POINT 적립",
                "수수료우대": "모든 은행, GS25 ATM / 해외 결제 및 ATM 인출수수료 무료",
                "유의사항": "꼭 확인하세요!"
            },
            "카드 이미지": "card_image/check_card\\436card.png"
        }
    },
    {
        "국민행복 체크카드 S2": {
            "혜택 요약": "의료(임신·출산) 3% 캐시백, 학습지/학원/서점 3% 캐시백, 영상/음원서비스 10% 캐시백",
            "연회비 상세안내": "국내전용(BC) 없음 해외겸용(mastercard) 없음",
            "주요 혜택": {
                "국민행복": "의료(임신·출산) / 보육(교육) 업종 3% 캐시백",
                "디지털구독": "언택트 라이프 업종(영상, 음원, 전자도서, 멤버십) 10% 캐시백",
                "해외": "해외가맹점(해외직구 포함) 이용금액 캐시백",
                "유의사항": "꼭 확인하세요!"
            },
            "카드 이미지": "card_image/check_card\\722card.png"
        }
    },
    {
        "트래블제로카드": {
            "혜택 요약": "환전 수수료 ZERO (환율 100% 우대), 해외 결제/ATM 수수료 ZERO, 국내 실적/한도없이 캐시백/할인",
            "연회비 상세안내": "해외겸용(mastercard) 없음 발급비용 무료(단, 추가/재 발급 시 3,000원)",
            "주요 혜택": {
                "해외이용": "해외 결제 시점, 알아서 자동 환전 + 환전 수수료 면제",
                "수수료우대": "해외 가맹점 결제 수수료 면제해외 ATM 출금 수수료 면제",
                "해외직구": "해외 직구도 수수료 면제",
                "적립": "국내 온라인/오프라인 실적 상관없이 무조건 무제한 0.3% 캐시백",
                "할인": "국내 커피빈 / CGV 실적 상관없이 무조건 즉시할인",
                "교통": "국내 대중교통 기능 지원",
                "유의사항": "꼭 확인하세요!"
            },
            "카드 이미지": "card_image/check_card\\2582card.png"
        }
    }
]